biggusdictus/__init__.py
biggusdictus/__main__.py
biggusdictus/funcs.py
biggusdictus/load.py
biggusdictus/scheme.py
biggusdictus-0.0.5.dist-info/licenses/LICENSE
biggusdictus-0.0.5.dist-info/METADATA
biggusdictus-0.0.5.dist-info/WHEEL
biggusdictus-0.0.5.dist-info/entry_points.txt
biggusdictus-0.0.5.dist-info/top_level.txt
biggusdictus-0.0.5.dist-info/RECORD
