Metadata-Version: 2.4
Name: biggusdictus
Version: 0.0.5
Summary: Validator for dictionaries
Author-email: Dominik Stanisław Suchora <hexderm@gmail.com>
License: GPLv3
Project-URL: Homepage, https://github.com/TUVIMEN/biggusdictus
Keywords: validation,schema
Classifier: Development Status :: 4 - Beta
Classifier: License :: OSI Approved :: GNU General Public License v3 (GPLv3)
Classifier: Operating System :: OS Independent
Classifier: Programming Language :: Python :: 3
Classifier: Programming Language :: Python :: 3.8
Classifier: Programming Language :: Python :: 3.9
Classifier: Programming Language :: Python :: 3.10
Classifier: Programming Language :: Python :: 3.11
Classifier: Programming Language :: Python :: 3.12
Classifier: Programming Language :: Python :: 3.13
Classifier: Programming Language :: Python :: 3 :: Only
Requires-Python: >=3.8
License-File: LICENSE
Dynamic: license-file
